Workbook

Sheet Superstore analyse
A1: Row ID | B1: Order ID | C1: Order Date | D1: Ship Date | E1: Ship Mode | F1: Customer ID | G1: Customer Name | H1: Segment | I1: Country | J1: City | K1: State | L1: Postal Code | M1: Region | N1: Product ID | O1: Category | P1: Sub-Category | Q1: Product Name | R1: Sales | S1: Quantity | T1: Discount | U1: Profit | Y1: Discount | Z1: Average Profit | AC1: PRODUCTS NAME | AD1: SALES | AE1: TOP 10 PRODUCTS
A2: 1 | B2: CA-2016-152156 | C2: 42682 | D2: 42685 | E2: Second Class | F2: CG-12520 | G2: Claire Gute | H2: Consumer | I2: United States | J2: Henderson | K2: Kentucky | L2: 42420 | M2: South | N2: FUR-BO-10001798 | O2: Furniture | P2: Bookcases | Q2: Bush Somerset Collection Bookcase | R2: 261.96 | S2: 2 | T2: 0 | U2: 41.9136 | W2: =ISNUMBER(J2) -> FALSE | Y2: 0 | Z2: =AVERAGEIF($T$2:$T$9995,Y2,$U$2:$U$9995) -> 66.900292 | AC2: {=_xlfn.UNIQUE($Q$2:$Q$9995)} -> Bush Somerset Collection Bookcase | AD2: =SUMIF($Q$2:$Q$9995,AC2,$R$2:$R$9995) -> 1263.957 | AE2: {=INDEX(_xlfn._xlws.SORT(AC2:AD9995,2,-1),_xlfn.SEQUENCE(10),{1,2})} -> Canon imageCLASS 2200 Advanced Copier | AF2: 61599.824
A3: 2 | B3: CA-2016-152156 | C3: 42682 | D3: 42685 | E3: Second Class | F3: CG-12520 | G3: Claire Gute | H3: Consumer | I3: United States | J3: Henderson | K3: Kentucky | L3: 42420 | M3: South | N3: FUR-CH-10000454 | O3: Furniture | P3: Chairs | Q3: Hon Deluxe Fabric Upholstered Stacking Chairs, Rounded Back | R3: 731.94 | S3: 3 | T3: 0 | U3: 219.582 | Y3: 0 | Z3: =AVERAGEIF($T$2:$T$9995,Y3,$U$2:$U$9995) -> 66.900292 | AC3: Hon Deluxe Fabric Upholstered Stacking Chairs, Rounded Back | AD3: =SUMIF($Q$2:$Q$9995,AC3,$R$2:$R$9995) -> 10637.528 | AE3: Fellowes PB500 Electric Punch Plastic Comb Binding Machine with Manual Bind | AF3: 27453.384
A4: 3 | B4: CA-2016-138688 | C4: 42533 | D4: 42537 | E4: Second Class | F4: DV-13045 | G4: Darrin Van Huff | H4: Corporate | I4: United States | J4: Los Angeles | K4: California | L4: 90036 | M4: West | N4: OFF-LA-10000240 | O4: Office Supplies | P4: Labels | Q4: Self-Adhesive Address Labels for Typewriters by Universal | R4: 14.62 | S4: 2 | T4: 0 | U4: 6.8714 | W4: =SUM(Superstore[Sales]) -> 2297200.9 | Y4: 0 | Z4: =AVERAGEIF($T$2:$T$9995,Y4,$U$2:$U$9995) -> 66.900292 | AC4: Self-Adhesive Address Labels for Typewriters by Universal | AD4: =SUMIF($Q$2:$Q$9995,AC4,$R$2:$R$9995) -> 153.51 | AE4: Cisco TelePresence System EX90 Videoconferencing Unit | AF4: 22638.48
A5: 4 | B5: US-2015-108966 | C5: 42288 | D5: 42295 | E5: Standard Class | F5: SO-20335 | G5: Sean O'Donnell | H5: Consumer | I5: United States | J5: Fort Lauderdale | K5: Florida | L5: 33311 | M5: South | N5: FUR-TA-10000577 | O5: Furniture | P5: Tables | Q5: Bretford CR4500 Series Slim Rectangular Table | R5: 957.5775 | S5: 5 | T5: 0.45 | U5: -383.031 | W5: =ISNUMBER(R2) -> TRUE | Y5: 0.45 | Z5: =AVERAGEIF($T$2:$T$9995,Y5,$U$2:$U$9995) -> -226.64646 | AC5: Bretford CR4500 Series Slim Rectangular Table | AD5: =SUMIF($Q$2:$Q$9995,AC5,$R$2:$R$9995) -> 7242.768 | AE5: HON 5400 Series Task Chairs for Big and Tall | AF5: 21870.576
A6: 5 | B6: US-2015-108966 | C6: 42288 | D6: 42295 | E6: Standard Class | F6: SO-20335 | G6: Sean O'Donnell | H6: Consumer | I6: United States | J6: Fort Lauderdale | K6: Florida | L6: 33311 | M6: South | N6: OFF-ST-10000760 | O6: Office Supplies | P6: Storage | Q6: Eldon Fold 'N Roll Cart System | R6: 22.368 | S6: 2 | T6: 0.2 | U6: 2.5164 | Y6: 0.2 | Z6: =AVERAGEIF($T$2:$T$9995,Y6,$U$2:$U$9995) -> 24.702572 | AC6: Eldon Fold 'N Roll Cart System | AD6: =SUMIF($Q$2:$Q$9995,AC6,$R$2:$R$9995) -> 301.968 | AE6: GBC DocuBind TL300 Electric Binding System | AF6: 19823.479
A7: 6 | B7: CA-2014-115812 | C7: 41799 | D7: 41804 | E7: Standard Class | F7: BH-11710 | G7: Brosina Hoffman | H7: Consumer | I7: United States | J7: Los Angeles | K7: California | L7: 90032 | M7: West | N7: FUR-FU-10001487 | O7: Furniture | P7: Furnishings | Q7: Eldon Expressions Wood and Plastic Desk Accessories, Cherry Wood | R7: 48.86 | S7: 7 | T7: 0 | U7: 14.1694 | W7: =ISNUMBER(R3) -> TRUE | Y7: 0 | Z7: =AVERAGEIF($T$2:$T$9995,Y7,$U$2:$U$9995) -> 66.900292 | AC7: Eldon Expressions Wood and Plastic Desk Accessories, Cherry Wood | AD7: =SUMIF($Q$2:$Q$9995,AC7,$R$2:$R$9995) -> 160.54 | AE7: GBC Ibimaster 500 Manual ProClick Binding System | AF7: 19024.5
A8: 7 | B8: CA-2014-115812 | C8: 41799 | D8: 41804 | E8: Standard Class | F8: BH-11710 | G8: Brosina Hoffman | H8: Consumer | I8: United States | J8: Los Angeles | K8: California | L8: 90032 | M8: West | N8: OFF-AR-10002833 | O8: Office Supplies | P8: Art | Q8: Newell 322 | R8: 7.28 | S8: 4 | T8: 0 | U8: 1.9656 | Y8: 0 | Z8: =AVERAGEIF($T$2:$T$9995,Y8,$U$2:$U$9995) -> 66.900292 | AC8: Newell 322 | AD8: =SUMIF($Q$2:$Q$9995,AC8,$R$2:$R$9995) -> 30.576 | AE8: Hewlett Packard LaserJet 3310 Copier | AF8: 18839.686
A9: 8 | B9: CA-2014-115812 | C9: 41799 | D9: 41804 | E9: Standard Class | F9: BH-11710 | G9: Brosina Hoffman | H9: Consumer | I9: United States | J9: Los Angeles | K9: California | L9: 90032 | M9: West | N9: TEC-PH-10002275 | O9: Technology | P9: Phones | Q9: Mitel 5320 IP Phone VoIP phone | R9: 907.152 | S9: 6 | T9: 0.2 | U9: 90.7152 | Y9: 0.2 | Z9: =AVERAGEIF($T$2:$T$9995,Y9,$U$2:$U$9995) -> 24.702572 | AC9: Mitel 5320 IP Phone VoIP phone | AD9: =SUMIF($Q$2:$Q$9995,AC9,$R$2:$R$9995) -> 2116.688 | AE9: HP Designjet T520 Inkjet Large Format Printer - 24" Color | AF9: 18374.895
A10: 9 | B10: CA-2014-115812 | C10: 41799 | D10: 41804 | E10: Standard Class | F10: BH-11710 | G10: Brosina Hoffman | H10: Consumer | I10: United States | J10: Los Angeles | K10: California | L10: 90032 | M10: West | N10: OFF-BI-10003910 | O10: Office Supplies | P10: Binders | Q10: DXL Angle-View Binders with Locking Rings by Samsill | R10: 18.504 | S10: 3 | T10: 0.2 | U10: 5.7825 | Y10: 0.2 | Z10: =AVERAGEIF($T$2:$T$9995,Y10,$U$2:$U$9995) -> 24.702572 | AC10: DXL Angle-View Binders with Locking Rings by Samsill | AD10: =SUMIF($Q$2:$Q$9995,AC10,$R$2:$R$9995) -> 215.109 | AE10: GBC DocuBind P400 Electric Binding System | AF10: 17965.068
A11: 10 | B11: CA-2014-115812 | C11: 41799 | D11: 41804 | E11: Standard Class | F11: BH-11710 | G11: Brosina Hoffman | H11: Consumer | I11: United States | J11: Los Angeles | K11: California | L11: 90032 | M11: West | N11: OFF-AP-10002892 | O11: Office Supplies | P11: Appliances | Q11: Belkin F5C206VTEL 6 Outlet Surge | R11: 114.9 | S11: 5 | T11: 0 | U11: 34.47 | Y11: 0 | Z11: =AVERAGEIF($T$2:$T$9995,Y11,$U$2:$U$9995) -> 66.900292 | AC11: Belkin F5C206VTEL 6 Outlet Surge | AD11: =SUMIF($Q$2:$Q$9995,AC11,$R$2:$R$9995) -> 464.196 | AE11: High Speed Automatic Electric Letter Opener | AF11: 17030.312
A12: 11 | B12: CA-2014-115812 | C12: 41799 | D12: 41804 | E12: Standard Class | F12: BH-11710 | G12: Brosina Hoffman | H12: Consumer | I12: United States | J12: Los Angeles | K12: California | L12: 90032 | M12: West | N12: FUR-TA-10001539 | O12: Furniture | P12: Tables | Q12: Chromcraft Rectangular Conference Tables | R12: 1706.184 | S12: 9 | T12: 0.2 | U12: 85.3092 | Y12: 0.2 | Z12: =AVERAGEIF($T$2:$T$9995,Y12,$U$2:$U$9995) -> 24.702572 | AC12: Chromcraft Rectangular Conference Tables | AD12: =SUMIF($Q$2:$Q$9995,AC12,$R$2:$R$9995) -> 4952.673
A13: 12 | B13: CA-2014-115812 | C13: 41799 | D13: 41804 | E13: Standard Class | F13: BH-11710 | G13: Brosina Hoffman | H13: Consumer | I13: United States | J13: Los Angeles | K13: California | L13: 90032 | M13: West | N13: TEC-PH-10002033 | O13: Technology | P13: Phones | Q13: Konftel 250 Conference phone - Charcoal black | R13: 911.424 | S13: 4 | T13: 0.2 | U13: 68.3568 | Y13: 0.2 | Z13: =AVERAGEIF($T$2:$T$9995,Y13,$U$2:$U$9995) -> 24.702572 | AC13: Konftel 250 Conference phone - Charcoal black | AD13: =SUMIF($Q$2:$Q$9995,AC13,$R$2:$R$9995) -> 2221.596
A14: 13 | B14: CA-2017-114412 | C14: 42840 | D14: 42845 | E14: Standard Class | F14: AA-10480 | G14: Andrew Allen | H14: Consumer | I14: United States | J14: Concord | K14: North Carolina | L14: 28027 | M14: South | N14: OFF-PA-10002365 | O14: Office Supplies | P14: Paper | Q14: Xerox 1967 | R14: 15.552 | S14: 3 | T14: 0.2 | U14: 5.4432 | Y14: 0.2 | Z14: =AVERAGEIF($T$2:$T$9995,Y14,$U$2:$U$9995) -> 24.702572 | AC14: Xerox 1967 | AD14: =SUMIF($Q$2:$Q$9995,AC14,$R$2:$R$9995) -> 89.424
A15: 14 | B15: CA-2016-161389 | C15: 42709 | D15: 42714 | E15: Standard Class | F15: IM-15070 | G15: Irene Maddox | H15: Consumer | I15: United States | J15: Seattle | K15: Washington | L15: 98103 | M15: West | N15: OFF-BI-10003656 | O15: Office Supplies | P15: Binders | Q15: Fellowes PB200 Plastic Comb Binding Machine | R15: 407.976 | S15: 3 | T15: 0.2 | U15: 132.5922 | Y15: 0.2 | Z15: =AVERAGEIF($T$2:$T$9995,Y15,$U$2:$U$9995) -> 24.702572 | AC15: Fellowes PB200 Plastic Comb Binding Machine | AD15: =SUMIF($Q$2:$Q$9995,AC15,$R$2:$R$9995) -> 4181.754
A16: 15 | B16: US-2015-118983 | C16: 42330 | D16: 42334 | E16: Standard Class | F16: HP-14815 | G16: Harold Pawlan | H16: Home Office | I16: United States | J16: Fort Worth | K16: Texas | L16: 76106 | M16: Central | N16: OFF-AP-10002311 | O16: Office Supplies | P16: Appliances | Q16: Holmes Replacement Filter for HEPA Air Cleaner, Very Large Room, HEPA Filter | R16: 68.81 | S16: 5 | T16: 0.8 | U16: -123.858 | Y16: 0.8 | Z16: =AVERAGEIF($T$2:$T$9995,Y16,$U$2:$U$9995) -> -101.7968 | AC16: Holmes Replacement Filter for HEPA Air Cleaner, Very Large Room, HEPA Filter | AD16: =SUMIF($Q$2:$Q$9995,AC16,$R$2:$R$9995) -> 1383.081
A17: 16 | B17: US-2015-118983 | C17: 42330 | D17: 42334 | E17: Standard Class | F17: HP-14815 | G17: Harold Pawlan | H17: Home Office | I17: United States | J17: Fort Worth | K17: Texas | L17: 76106 | M17: Central | N17: OFF-BI-10000756 | O17: Office Supplies | P17: Binders | Q17: Storex DuraTech Recycled Plastic Frosted Binders | R17: 2.544 | S17: 3 | T17: 0.8 | U17: -3.816 | Y17: 0.8 | Z17: =AVERAGEIF($T$2:$T$9995,Y17,$U$2:$U$9995) -> -101.7968 | AC17: Storex DuraTech Recycled Plastic Frosted Binders | AD17: =SUMIF($Q$2:$Q$9995,AC17,$R$2:$R$9995) -> 94.128
A18: 17 | B18: CA-2014-105893 | C18: 41954 | D18: 41961 | E18: Standard Class | F18: PK-19075 | G18: Pete Kriz | H18: Consumer | I18: United States | J18: Madison | K18: Wisconsin | L18: 53711 | M18: Central | N18: OFF-ST-10004186 | O18: Office Supplies | P18: Storage | Q18: Stur-D-Stor Shelving, Vertical 5-Shelf: 72"H x 36"W x 18 1/2"D | R18: 665.88 | S18: 6 | T18: 0 | U18: 13.3176 | Y18: 0 | Z18: =AVERAGEIF($T$2:$T$9995,Y18,$U$2:$U$9995) -> 66.900292 | AC18: Stur-D-Stor Shelving, Vertical 5-Shelf: 72"H x 36"W x 18 1/2"D | AD18: =SUMIF($Q$2:$Q$9995,AC18,$R$2:$R$9995) -> 2552.54
A19: 18 | B19: CA-2014-167164 | C19: 41772 | D19: 41774 | E19: Second Class | F19: AG-10270 | G19: Alejandro Grove | H19: Consumer | I19: United States | J19: West Jordan | K19: Utah | L19: 84084 | M19: West | N19: OFF-ST-10000107 | O19: Office Supplies | P19: Storage | Q19: Fellowes Super Stor/Drawer | R19: 55.5 | S19: 2 | T19: 0 | U19: 9.99 | Y19: 0 | Z19: =AVERAGEIF($T$2:$T$9995,Y19,$U$2:$U$9995) -> 66.900292 | AC19: Fellowes Super Stor/Drawer | AD19: =SUMIF($Q$2:$Q$9995,AC19,$R$2:$R$9995) -> 477.3
A20: 19 | B20: CA-2014-143336 | C20: 41878 | D20: 41883 | E20: Second Class | F20: ZD-21925 | G20: Zuschuss Donatelli | H20: Consumer | I20: United States | J20: San Francisco | K20: California | L20: 94109 | M20: West | N20: OFF-AR-10003056 | O20: Office Supplies | P20: Art | Q20: Newell 341 | R20: 8.56 | S20: 2 | T20: 0 | U20: 2.4824 | Y20: 0 | Z20: =AVERAGEIF($T$2:$T$9995,Y20,$U$2:$U$9995) -> 66.900292 | AC20: Newell 341 | AD20: =SUMIF($Q$2:$Q$9995,AC20,$R$2:$R$9995) -> 96.728
A21: 20 | B21: CA-2014-143336 | C21: 41878 | D21: 41883 | E21: Second Class | F21: ZD-21925 | G21: Zuschuss Donatelli | H21: Consumer | I21: United States | J21: San Francisco | K21: California | L21: 94109 | M21: West | N21: TEC-PH-10001949 | O21: Technology | P21: Phones | Q21: Cisco SPA 501G IP Phone | R21: 213.48 | S21: 3 | T21: 0.2 | U21: 16.011 | Y21: 0.2 | Z21: =AVERAGEIF($T$2:$T$9995,Y21,$U$2:$U$9995) -> 24.702572 | AC21: Cisco SPA 501G IP Phone | AD21: =SUMIF($Q$2:$Q$9995,AC21,$R$2:$R$9995) -> 213.48
A22: 21 | B22: CA-2014-143336 | C22: 41878 | D22: 41883 | E22: Second Class | F22: ZD-21925 | G22: Zuschuss Donatelli | H22: Consumer | I22: United States | J22: San Francisco | K22: California | L22: 94109 | M22: West | N22: OFF-BI-10002215 | O22: Office Supplies | P22: Binders | Q22: Wilson Jones Hanging View Binder, White, 1" | R22: 22.72 | S22: 4 | T22: 0.2 | U22: 7.384 | Y22: 0.2 | Z22: =AVERAGEIF($T$2:$T$9995,Y22,$U$2:$U$9995) -> 24.702572 | AC22: Wilson Jones Hanging View Binder, White, 1" | AD22: =SUMIF($Q$2:$Q$9995,AC22,$R$2:$R$9995) -> 143.42
A23: 22 | B23: CA-2016-137330 | C23: 42713 | D23: 42717 | E23: Standard Class | F23: KB-16585 | G23: Ken Black | H23: Corporate | I23: United States | J23: Fremont | K23: Nebraska | L23: 68025 | M23: Central | N23: OFF-AR-10000246 | O23: Office Supplies | P23: Art | Q23: Newell 318 | R23: 19.46 | S23: 7 | T23: 0 | U23: 5.0596 | Y23: 0 | Z23: =AVERAGEIF($T$2:$T$9995,Y23,$U$2:$U$9995) -> 66.900292 | AC23: Newell 318 | AD23: =SUMIF($Q$2:$Q$9995,AC23,$R$2:$R$9995) -> 61.716
... A1851: 1850 | B1851: CA-2015-160472 | C1851: 42205 | D1851: 42210 | E1851: Second Class | F1851: RK-19300 | G1851: Ralph Kennedy | H1851: Consumer | I1851: United States | J1851: South Bend | K1851: Indiana | L1851: 46614 | M1851: Central | N1851: OFF-ST-10000464 | O1851: Office Supplies | P1851: Storage | Q1851: Multi-Use Personal File Cart and Caster Set, Three Stacking Bins | R1851: 34.76 | S1851: 1 | T1851: 0 | U1851: 9.7328 | Y1851: 0 | Z1851: =AVERAGEIF($T$2:$T$9995,Y1851,$U$2:$U$9995) -> 66.900292 | AC1851: Eldon Jumbo ProFile Portable File Boxes Graphite/Black | AD1851: =SUMIF($Q$2:$Q$9995,AC1851,$R$2:$R$9995) -> 36.744
A1852: 1851 | B1852: CA-2015-160472 | C1852: 42205 | D1852: 42210 | E1852: Second Class | F1852: RK-19300 | G1852: Ralph Kennedy | H1852: Consumer | I1852: United States | J1852: South Bend | K1852: Indiana | L1852: 46614 | M1852: Central | N1852: TEC-AC-10002253 | O1852: Technology | P1852: Accessories | Q1852: Imation Bio 8GB USB Flash Drive Imation Corp | R1852: 831.2 | S1852: 5 | T1852: 0 | U1852: 124.68 | Y1852: 0 | Z1852: =AVERAGEIF($T$2:$T$9995,Y1852,$U$2:$U$9995) -> 66.900292 | AD1852: =SUMIF($Q$2:$Q$9995,AC1852,$R$2:$R$9995) -> 0
A1853: 1852 | B1853: CA-2015-160472 | C1853: 42205 | D1853: 42210 | E1853: Second Class | F1853: RK-19300 | G1853: Ralph Kennedy | H1853: Consumer | I1853: United States | J1853: South Bend | K1853: Indiana | L1853: 46614 | M1853: Central | N1853: OFF-PA-10000528 | O1853: Office Supplies | P1853: Paper | Q1853: Xerox 1981 | R1853: 26.4 | S1853: 5 | T1853: 0 | U1853: 11.88 | Y1853: 0 | Z1853: =AVERAGEIF($T$2:$T$9995,Y1853,$U$2:$U$9995) -> 66.900292 | AD1853: =SUMIF($Q$2:$Q$9995,AC1853,$R$2:$R$9995) -> 0
A1854: 1853 | B1854: CA-2015-160472 | C1854: 42205 | D1854: 42210 | E1854: Second Class | F1854: RK-19300 | G1854: Ralph Kennedy | H1854: Consumer | I1854: United States | J1854: South Bend | K1854: Indiana | L1854: 46614 | M1854: Central | N1854: OFF-EN-10000483 | O1854: Office Supplies | P1854: Envelopes | Q1854: White Envelopes, White Envelopes with Clear Poly Window | R1854: 106.75 | S1854: 7 | T1854: 0 | U1854: 49.105 | Y1854: 0 | Z1854: =AVERAGEIF($T$2:$T$9995,Y1854,$U$2:$U$9995) -> 66.900292 | AD1854: =SUMIF($Q$2:$Q$9995,AC1854,$R$2:$R$9995) -> 0
A1855: 1854 | B1855: CA-2015-160472 | C1855: 42205 | D1855: 42210 | E1855: Second Class | F1855: RK-19300 | G1855: Ralph Kennedy | H1855: Consumer | I1855: United States | J1855: South Bend | K1855: Indiana | L1855: 46614 | M1855: Central | N1855: OFF-PA-10003129 | O1855: Office Supplies | P1855: Paper | Q1855: Tops White Computer Printout Paper | R1855: 97.82 | S1855: 2 | T1855: 0 | U1855: 45.9754 | Y1855: 0 | Z1855: =AVERAGEIF($T$2:$T$9995,Y1855,$U$2:$U$9995) -> 66.900292 | AD1855: =SUMIF($Q$2:$Q$9995,AC1855,$R$2:$R$9995) -> 0
A1856: 1855 | B1856: CA-2015-160472 | C1856: 42205 | D1856: 42210 | E1856: Second Class | F1856: RK-19300 | G1856: Ralph Kennedy | H1856: Consumer | I1856: United States | J1856: South Bend | K1856: Indiana | L1856: 46614 | M1856: Central | N1856: OFF-ST-10003442 | O1856: Office Supplies | P1856: Storage | Q1856: Eldon Portable Mobile Manager | R1856: 141.4 | S1856: 5 | T1856: 0 | U1856: 38.178 | Y1856: 0 | Z1856: =AVERAGEIF($T$2:$T$9995,Y1856,$U$2:$U$9995) -> 66.900292 | AD1856: =SUMIF($Q$2:$Q$9995,AC1856,$R$2:$R$9995) -> 0
A1857: 1856 | B1857: CA-2014-114643 | C1857: 41803 | D1857: 41807 | E1857: Standard Class | F1857: FM-14215 | G1857: Filia McAdams | H1857: Corporate | I1857: United States | J1857: Los Angeles | K1857: California | L1857: 90032 | M1857: West | N1857: OFF-AR-10003631 | O1857: Office Supplies | P1857: Art | Q1857: Staples in misc. colors | R1857: 14.52 | S1857: 3 | T1857: 0 | U1857: 4.7916 | Y1857: 0 | Z1857: =AVERAGEIF($T$2:$T$9995,Y1857,$U$2:$U$9995) -> 66.900292 | AD1857: =SUMIF($Q$2:$Q$9995,AC1857,$R$2:$R$9995) -> 0
A1858: 1857 | B1858: US-2017-158218 | C1858: 42867 | D1858: 42870 | E1858: Second Class | F1858: AC-10420 | G1858: Alyssa Crouse | H1858: Corporate | I1858: United States | J1858: Houston | K1858: Texas | L1858: 77041 | M1858: Central | N1858: OFF-ST-10000563 | O1858: Office Supplies | P1858: Storage | Q1858: Fellowes Bankers Box Stor/Drawer Steel Plus | R1858: 127.92 | S1858: 5 | T1858: 0.2 | U1858: -15.99 | Y1858: 0.2 | Z1858: =AVERAGEIF($T$2:$T$9995,Y1858,$U$2:$U$9995) -> 24.702572 | AD1858: =SUMIF($Q$2:$Q$9995,AC1858,$R$2:$R$9995) -> 0
A1859: 1858 | B1859: US-2017-158218 | C1859: 42867 | D1859: 42870 | E1859: Second Class | F1859: AC-10420 | G1859: Alyssa Crouse | H1859: Corporate | I1859: United States | J1859: Houston | K1859: Texas | L1859: 77041 | M1859: Central | N1859: OFF-BI-10002133 | O1859: Office Supplies | P1859: Binders | Q1859: Wilson Jones Elliptical Ring 3 1/2" Capacity Binders, 800 sheets | R1859: 34.24 | S1859: 4 | T1859: 0.8 | U1859: -53.072 | Y1859: 0.8 | Z1859: =AVERAGEIF($T$2:$T$9995,Y1859,$U$2:$U$9995) -> -101.7968 | AD1859: =SUMIF($Q$2:$Q$9995,AC1859,$R$2:$R$9995) -> 0
A1860: 1859 | B1860: CA-2015-121608 | C1860: 42250 | D1860: 42252 | E1860: First Class | F1860: JB-15400 | G1860: Jennifer Braxton | H1860: Corporate | I1860: United States | J1860: Bristol | K1860: Connecticut | L1860: 6010 | M1860: East | N1860: OFF-AP-10002311 | O1860: Office Supplies | P1860: Appliances | Q1860: Holmes Replacement Filter for HEPA Air Cleaner, Very Large Room, HEPA Filter | R1860: 137.62 | S1860: 2 | T1860: 0 | U1860: 60.5528 | Y1860: 0 | Z1860: =AVERAGEIF($T$2:$T$9995,Y1860,$U$2:$U$9995) -> 66.900292 | AD1860: =SUMIF($Q$2:$Q$9995,AC1860,$R$2:$R$9995) -> 0
A1861: 1860 | B1861: CA-2015-121608 | C1861: 42250 | D1861: 42252 | E1861: First Class | F1861: JB-15400 | G1861: Jennifer Braxton | H1861: Corporate | I1861: United States | J1861: Bristol | K1861: Connecticut | L1861: 6010 | M1861: East | N1861: TEC-PH-10004959 | O1861: Technology | P1861: Phones | Q1861: Classic Ivory Antique Telephone ZL1810 | R1861: 100.49 | S1861: 1 | T1861: 0 | U1861: 25.1225 | Y1861: 0 | Z1861: =AVERAGEIF($T$2:$T$9995,Y1861,$U$2:$U$9995) -> 66.900292 | AD1861: =SUMIF($Q$2:$Q$9995,AC1861,$R$2:$R$9995) -> 0
A1862: 1861 | B1862: US-2017-121251 | C1862: 42820 | D1862: 42821 | E1862: First Class | F1862: GM-14440 | G1862: Gary McGarr | H1862: Consumer | I1862: United States | J1862: New York City | K1862: New York | L1862: 10009 | M1862: East | N1862: FUR-BO-10001918 | O1862: Furniture | P1862: Bookcases | Q1862: Sauder Forest Hills Library with Doors, Woodland Oak Finish | R1862: 257.568 | S1862: 2 | T1862: 0.2 | U1862: -28.9764 | Y1862: 0.2 | Z1862: =AVERAGEIF($T$2:$T$9995,Y1862,$U$2:$U$9995) -> 24.702572 | AD1862: =SUMIF($Q$2:$Q$9995,AC1862,$R$2:$R$9995) -> 0
A1863: 1862 | B1863: US-2017-121251 | C1863: 42820 | D1863: 42821 | E1863: First Class | F1863: GM-14440 | G1863: Gary McGarr | H1863: Consumer | I1863: United States | J1863: New York City | K1863: New York | L1863: 10009 | M1863: East | N1863: TEC-PH-10004896 | O1863: Technology | P1863: Phones | Q1863: Nokia Lumia 521 (T-Mobile) | R1863: 119.96 | S1863: 4 | T1863: 0 | U1863: 33.5888 | Y1863: 0 | Z1863: =AVERAGEIF($T$2:$T$9995,Y1863,$U$2:$U$9995) -> 66.900292 | AD1863: =SUMIF($Q$2:$Q$9995,AC1863,$R$2:$R$9995) -> 0
... A9995: 9994 | B9995: CA-2017-119914 | C9995: 42859 | D9995: 42864 | E9995: Second Class | F9995: CC-12220 | G9995: Chris Cortes | H9995: Consumer | I9995: United States | J9995: Westminster | K9995: California | L9995: 92683 | M9995: West | N9995: OFF-AP-10002684 | O9995: Office Supplies | P9995: Appliances | Q9995: Acco 7-Outlet Masterpiece Power Center, Wihtout Fax/Phone Line Protection | R9995: 243.16 | S9995: 2 | T9995: 0 | U9995: 72.948 | Y9995: 0 | Z9995: =AVERAGEIF($T$2:$T$9995,Y9995,$U$2:$U$9995) -> 66.900292 | AD9995: =SUMIF($Q$2:$Q$9995,AC9995,$R$2:$R$9995) -> 0

Sheet Analysis
B2: QUANTITY | C2: DISCOUNT | D2: SALES | E2: PROFIT | H2: CATEGORY | I2: SALES | J2: PROFIT | K2: Profit Margin
B3: =MIN('Superstore analyse'!S:S) -> 1 | C3: =MIN('Superstore analyse'!T:T) -> 0 | D3: =MIN('Superstore analyse'!R:R) -> 0.444 | E3: =MIN('Superstore analyse'!U:U) -> -6599.978 | H3: Furniture | I3: =SUMIF('Superstore analyse'!$O$2:$O$9995,"Furniture",'Superstore analyse'!$R$2:$R$9995) -> 741999.8 | J3: =SUMIF('Superstore analyse'!$O$2:$O$9995,"Furniture",'Superstore analyse'!$U$2:$U$9995) -> 18451.273 | K3: =J3/I3 -> 0.024866951
B4: =MAX('Superstore analyse'!S:S) -> 14 | C4: =MAX('Superstore analyse'!T:T) -> 0.8 | D4: =MAX('Superstore analyse'!R:R) -> 22638.48 | E4: =MAX('Superstore analyse'!U:U) -> 8399.976 | H4: Office Supplies | I4: =SUMIF('Superstore analyse'!$O$2:$O$9995,"Office Supplies",'Superstore analyse'!$R$2:$R$9995) -> 719047.03 | J4: =SUMIF('Superstore analyse'!$O$2:$O$9995,"Office Supplies",'Superstore analyse'!$U$2:$U$9995) -> 122490.8 | K4: =J4/I4 -> 0.17035158
B5: =AVERAGE('Superstore analyse'!S:S) -> 3.7895737 | C5: =AVERAGE('Superstore analyse'!T:T) -> 0.15620272 | D5: =AVERAGE('Superstore analyse'!R:R) -> 229.858 | E5: =AVERAGE('Superstore analyse'!U:U) -> 28.656896 | H5: Technology | I5: =SUMIF('Superstore analyse'!$O$2:$O$9995,"Technology",'Superstore analyse'!$R$2:$R$9995) -> 836154.03 | J5: =SUMIF('Superstore analyse'!$O$2:$O$9995,"Technology",'Superstore analyse'!$U$2:$U$9995) -> 145454.95 | K5: =J5/I5 -> 0.17395712
A6: TOTAL | B6: =SUM('Superstore analyse'!S:S) -> 37873 | C6: =SUM('Superstore analyse'!T:T) -> 1561.09 | D6: =SUM('Superstore analyse'!R:R) -> 2297200.9 | E6: =SUM('Superstore analyse'!U:U) -> 286397.02
B9: Number of Orders | C9: =COUNTA(_xlfn.UNIQUE('Superstore analyse'!B:B)) -> 5011
B10: Average Order Value | C10: =Tabela7[[#Totals],[SALES]]/C9 -> 458.43162
B11: Profit Margin | C11: =Tabela7[[#Totals],[PROFIT]]/Tabela7[[#Totals],[SALES]] -> 0.12467217
J25: YEAR | K25: SALES
J26: 2014 | K26: =SUMIFS('Superstore analyse'!$R$2:$R$9995,'Superstore analyse'!$C$2:$C$9995,">="&DATE(J26,1,1),'Superstore analyse'!$C$2:$C$9995,"<"&DATE(J26+1,1,1)) -> 484247.5
J27: 2015 | K27: =SUMIFS('Superstore analyse'!$R$2:$R$9995,'Superstore analyse'!$C$2:$C$9995,">="&DATE(J27,1,1),'Superstore analyse'!$C$2:$C$9995,"<"&DATE(J27+1,1,1)) -> 470532.51
J28: 2016 | K28: =SUMIFS('Superstore analyse'!$R$2:$R$9995,'Superstore analyse'!$C$2:$C$9995,">="&DATE(J28,1,1),'Superstore analyse'!$C$2:$C$9995,"<"&DATE(J28+1,1,1)) -> 609205.6
J29: 2017 | K29: =SUMIFS('Superstore analyse'!$R$2:$R$9995,'Superstore analyse'!$C$2:$C$9995,">="&DATE(J29,1,1),'Superstore analyse'!$C$2:$C$9995,"<"&DATE(J29+1,1,1)) -> 733215.26

Sheet Data Quality
A1: Check | B1: Result
A2: Number of rows | B2: 9995
A3: Number of columns | B3: 21
A4: Missing values | B4: 0
A5: Duplicate rows | B5: 0
